openTB/__init__.py
openTB/openTB.py
openTB-0.0.3.dist-info/LICENSE
openTB-0.0.3.dist-info/METADATA
openTB-0.0.3.dist-info/WHEEL
openTB-0.0.3.dist-info/top_level.txt
openTB-0.0.3.dist-info/RECORD
